phi_masker_utils/__init__.py
phi_masker_utils/console_helper.py
phi_masker_utils/constants.py
phi_masker_utils/file_utils.py
phi_masker_utils/mask_file.py
phi_masker_utils/masker.py
phi_masker_utils/system_caller.py
phi_masker_utils/conf/config.yaml
phi_masker_utils-0.1.0.dist-info/AUTHORS.rst
phi_masker_utils-0.1.0.dist-info/LICENSE
phi_masker_utils-0.1.0.dist-info/METADATA
phi_masker_utils-0.1.0.dist-info/WHEEL
phi_masker_utils-0.1.0.dist-info/entry_points.txt
phi_masker_utils-0.1.0.dist-info/top_level.txt
phi_masker_utils-0.1.0.dist-info/RECORD
