Metadata-Version: 2.1
Name: phi_masker_utils
Version: 0.1.0
Summary: Collection of Python modules for masking PHI in delimited files and Excel worksheets.
Home-page: https://github.com/jai-python3/phi-masker-utils
Author: Jaideep Sundaram
Author-email: jai.python3@gmail.com
Keywords: phi_masker_utils
Classifier: Development Status :: 2 - Pre-Alpha
Classifier: Intended Audience :: Developers
Classifier: Natural Language :: English
Classifier: Programming Language :: Python :: 3
Classifier: Programming Language :: Python :: 3.6
Classifier: Programming Language :: Python :: 3.7
Classifier: Programming Language :: Python :: 3.8
Requires-Python: >=3.6
License-File: LICENSE
License-File: AUTHORS.rst
Requires-Dist: Click>=7.0
Requires-Dist: faker
Requires-Dist: Rich
Requires-Dist: PyYAML
